aws_lambda_powertools/__init__.py
aws_lambda_powertools/event_handler/__init__.py
aws_lambda_powertools/event_handler/api_gateway.py
aws_lambda_powertools/event_handler/appsync.py
aws_lambda_powertools/event_handler/bedrock_agent.py
aws_lambda_powertools/event_handler/bedrock_agent_function.py
aws_lambda_powertools/event_handler/content_types.py
aws_lambda_powertools/event_handler/events_appsync/__init__.py
aws_lambda_powertools/event_handler/events_appsync/_registry.py
aws_lambda_powertools/event_handler/events_appsync/appsync_events.py
aws_lambda_powertools/event_handler/events_appsync/base.py
aws_lambda_powertools/event_handler/events_appsync/exceptions.py
aws_lambda_powertools/event_handler/events_appsync/functions.py
aws_lambda_powertools/event_handler/events_appsync/router.py
aws_lambda_powertools/event_handler/events_appsync/types.py
aws_lambda_powertools/event_handler/exception_handling.py
aws_lambda_powertools/event_handler/exceptions.py
aws_lambda_powertools/event_handler/graphql_appsync/__init__.py
aws_lambda_powertools/event_handler/graphql_appsync/_registry.py
aws_lambda_powertools/event_handler/graphql_appsync/base.py
aws_lambda_powertools/event_handler/graphql_appsync/exceptions.py
aws_lambda_powertools/event_handler/graphql_appsync/router.py
aws_lambda_powertools/event_handler/lambda_function_url.py
aws_lambda_powertools/event_handler/middlewares/__init__.py
aws_lambda_powertools/event_handler/middlewares/base.py
aws_lambda_powertools/event_handler/middlewares/openapi_validation.py
aws_lambda_powertools/event_handler/middlewares/schema_validation.py
aws_lambda_powertools/event_handler/openapi/__init__.py
aws_lambda_powertools/event_handler/openapi/compat.py
aws_lambda_powertools/event_handler/openapi/config.py
aws_lambda_powertools/event_handler/openapi/constants.py
aws_lambda_powertools/event_handler/openapi/dependant.py
aws_lambda_powertools/event_handler/openapi/encoders.py
aws_lambda_powertools/event_handler/openapi/exceptions.py
aws_lambda_powertools-3.22.1.dist-info/LICENSE
aws_lambda_powertools-3.22.1.dist-info/METADATA
aws_lambda_powertools-3.22.1.dist-info/WHEEL
aws_lambda_powertools-3.22.1.dist-info/RECORD
