Metadata-Version: 2.3
Name: aws_lambda_powertools
Version: 3.22.1
Summary: Powertools for AWS Lambda (Python) is a developer toolkit to implement Serverless best practices and increase developer velocity.
License: MIT
Keywords: aws_lambda_powertools,aws,tracing,logging,lambda,powertools,feature_flags,idempotency,middleware
Author: Amazon Web Services
Requires-Python: >=3.9,<4.0.0
Classifier: Development Status :: 5 - Production/Stable
Classifier: Intended Audience :: Developers
Classifier: License :: OSI Approved :: MIT License
Classifier: License :: OSI Approved :: MIT No Attribution License (MIT-0)
Classifier: Natural Language :: English
Classifier: Programming Language :: Python :: 3
Classifier: Programming Language :: Python :: 3.9
Classifier: Programming Language :: Python :: 3.10
Classifier: Programming Language :: Python :: 3.11
Classifier: Programming Language :: Python :: 3.12
Classifier: Programming Language :: Python :: 3.13
Provides-Extra: all
Provides-Extra: aws-sdk
Provides-Extra: datadog
Provides-Extra: datamasking
Provides-Extra: kafka-consumer-avro
Provides-Extra: kafka-consumer-protobuf
Provides-Extra: parser
Provides-Extra: redis
Provides-Extra: tracer
Provides-Extra: validation
Provides-Extra: valkey
Requires-Dist: avro (>=1.12.0,<2.0.0) ; extra == "kafka-consumer-avro"
Requires-Dist: aws-encryption-sdk (>=3.1.1,<5.0.0) ; extra == "all" or extra == "datamasking"
Requires-Dist: aws-xray-sdk (>=2.8.0,<3.0.0) ; extra == "tracer" or extra == "all"
Requires-Dist: boto3 (>=1.34.32,<2.0.0) ; extra == "aws-sdk"
Requires-Dist: datadog-lambda (>=6.106.0,<7.0.0) ; extra == "datadog"
Requires-Dist: fastjsonschema (>=2.14.5,<3.0.0) ; extra == "validation" or extra == "all"
Requires-Dist: jmespath (>=1.0.1,<2.0.0)
Requires-Dist: jsonpath-ng (>=1.6.0,<2.0.0) ; extra == "all" or extra == "datamasking"
Requires-Dist: protobuf (>=6.30.2,<7.0.0) ; extra == "kafka-consumer-protobuf"
Requires-Dist: pydantic (>=2.4.0,<3.0.0) ; extra == "parser" or extra == "all"
Requires-Dist: pydantic-settings (>=2.6.1,<3.0.0) ; extra == "all"
Requires-Dist: redis (>=4.4,<8.0) ; extra == "redis"
Requires-Dist: typing-extensions (>=4.11.0,<5.0.0)
Requires-Dist: valkey-glide (>=1.3.5,<3.0) ; extra == "valkey"
Project-URL: Documentation, https://docs.powertools.aws.dev/lambda/python/
Project-URL: Issue tracker, https://github.com/aws-powertools/powertools-lambda-python/issues
Project-URL: Repository, https://github.com/aws-powertools/powertools-lambda-python
Project-URL: Releases, https://github.com/aws-powertools/powertools-lambda-python/releases
